web3dummycti/__init__.py
web3dummycti/core.py
web3dummycti-0.1.0.dist-info/METADATA
web3dummycti-0.1.0.dist-info/WHEEL
web3dummycti-0.1.0.dist-info/top_level.txt
web3dummycti-0.1.0.dist-info/RECORD
