Metadata-Version: 2.4
Name: web3dummycti
Version: 0.1.0
Summary: web3dummycti
Author: brojafox
Requires-Python: >=3.6
Requires-Dist: requests>=2.0.0
Dynamic: author
Dynamic: requires-dist
Dynamic: requires-python
Dynamic: summary
